{
    "1":{
        "INF101":{
            "title":"Introdução à Computação",
            "short":["IAC"]
        },
        "INF102":{
            "title":"Lógica e Linguagem de Programação ",
            "short":["LELP"]
        },
        "GEC101":{
            "title":"Leitura e Produção Textual",
            "short":["LEPT"]
        },
        "EDC101":{
            "title":"Informática na Educação",
            "short":[""]
        },
        "MAT101":{
            "title":"Introdução à Matemática",
            "short":["IAM"]
        },
        "GEC102":{
            "title":"Ciência, Tecnologia e Sociedade",
            "short":["CTS"]
        }
    },
    "2":{
        "INF202":{
            "title":"Circuitos Digitais",
            "short":[""]
        },
        "INF201":{
            "title":"Estrutura de Dados",
            "short":[""]
        },
        "EDC201":{
            "title":"História da Educação",
            "short":[""]
        },
        "MAT201":{
            "title":"Cálculo Diferencial e Integral I",
            "short":[""]
        },
        "MAT202":{
            "title":"Álgebra Vetorial e Geometria Analítica",
            "short":[""]
        },
        "GEC201":{
            "title":"Inglês Técnico I",
            "short":[""]
        }
    },
    "3":{
        "INF301":{
            "title":"Programação Orientada a Objeto",
            "short":["POO"]
        },
        "INF304":{
            "title":"Análise e Projeto de Algoritmos",
            "short":[""]
        },
        "EDC301":{
            "title":"Filosofia na Educação",
            "short":[""]
        },
        "MAT301":{
            "title":"Cálculo Diferencial e Integral II",
            "short":[""]
        },
        "MAT302":{
            "title":"Álgebra Linear",
            "short":[""]
        },
        "INF302":{
            "title":"Organização de Arquivos de Dados",
            "short":[""]
        }
    },
    "4":{
        "INF401":{
            "title":"Arquitetura de Computadores",
            "short":[""]
        },
        "INF404":{
            "title":"Banco de Dados I",
            "short":[""]
        },
        "INF403":{
            "title":"Laboratório de Programação I",
            "short":[""]
        },
        "MAT401":{
            "title":"Probabilidade e Estatística",
            "short":[""]
        },
         "INF405":{
            "title":"Projeto Integrador I",
            "short":[""]
        },
        "INF402":{
            "title":"Linguagens Formais e Autômatos",
           "short":[""]
        }
    },
    "5":{
        "INF501":{
            "title":"Sistemas Operacionais",
            "short":[""]
        },
        "INF502":{
            "title":"Laboratório de Programação II",
            "short":[""]
        },
        "INF504":{
            "title":"Engenharia de Software",
            "short":[""]
        },
        "GEC501":{
            "title":"Metodologia de Pesquisa",
            "short":[""]
        },
        "INF503":{
            "title":"Teoria da Computação",
            "short":[""]
        },
        "INF505":{
            "title":"Banco de Dados II ",
            "short":[""]
        }
    },
    "6":{
        "INF605":{
            "title":"Web Design",
            "short":[""]
        },
        "INF601":{
            "title":"Grafos",
            "short":[""]
        },
        "INF603":{
            "title":"Interface Humano Computador - IHC",
            "short":[""]
        },
        "INF604":{
            "title":"Redes de Computadores",
            "short":[""]
        },
        "GEC601":{
            "title":"Empreendedorismo",
            "short":[""]
        },
        "INF602":{
            "title":"Laboratório de Programação III",
            "short":[""]
        }
    },
    "7":{
        "INF701":{
            "title":"Inteligência Artificial",
            "short":[""]
        },
        "INF702":{
            "title":"Sistemas Distribuídos",
            "short":[""]
        },
        "INF705":{
            "title":"Projeto integrador II",
            "short":[""]
        },
        "INF703":{
            "title":"Direito Aplicado a Informática",
            "short":[""]
        },
        "OPT701":{
            "title":"Internet das Coisas - IoT",
            "short":[""]
        },
        "INF704":{
            "title":"Gestão de Projetos",
            "short":[""]
        }
    },
    "8":{
        "INF803":{
            "title":"Compiladores",
            "short":[""]
        },
        "INF804":{
            "title":"Estágio",
            "short":[""]
        },
        "INF801":{
            "title":"Trabalho de Conclusão de Curso",
            "short":[""]
        },
        "INF805":{
            "title":"Tópicos Avançados em Programação",
            "short":[""]
        },
        "INF802":{
            "title":"Segurança da Informação",
            "short":[""]
        }
    },
    "Optativas":{
        "EDC4":{
            "title":"Libras",
            "short":[""]
        },
        "GEC04":{
            "title":"Relações Étnico-Racial e Diversidade",
            "short":[""]
        },
        "OPT801":{
            "title":"Optativo II",
            "short":[""]
        }
    }
}